infi.run_as_root-0.1.8-py2.7-nspkg.pth
infi/run_as_root/__init__.py
infi/run_as_root/__version__.py
infi/run_as_root/tests.py
infi/run_as_root/windows.py
infi.run_as_root-0.1.8.dist-info/LICENSE
infi.run_as_root-0.1.8.dist-info/METADATA
infi.run_as_root-0.1.8.dist-info/WHEEL
infi.run_as_root-0.1.8.dist-info/entry_points.txt
infi.run_as_root-0.1.8.dist-info/namespace_packages.txt
infi.run_as_root-0.1.8.dist-info/top_level.txt
infi.run_as_root-0.1.8.dist-info/RECORD
