Metadata-Version: 2.1
Name: infi.run-as-root
Version: 0.1.8
Summary: library for ensuring the user has root privileges
Home-page: https://github.com/Infinidat/infi.run_as_root
Author: Arnon Yaari
Author-email: arnony@infinidat.com
License: BSD
Platform: UNKNOWN
Classifier: Intended Audience :: Developers
Classifier: Intended Audience :: System Administrators
Classifier: License :: OSI Approved :: BSD License
Classifier: Operating System :: OS Independent
Classifier: Programming Language :: Python
Classifier: Programming Language :: Python :: 2
Classifier: Programming Language :: Python :: 3
Classifier: Topic :: Software Development :: Libraries :: Python Modules
Requires-Dist: infi.pyutils
Requires-Dist: setuptools
